fncbook/__init__.py
fncbook/chapter01.py
fncbook/chapter02.py
fncbook/chapter03.py
fncbook/chapter04.py
fncbook/chapter05.py
fncbook/chapter06.py
fncbook/chapter08.py
fncbook/chapter09.py
fncbook/chapter10.py
fncbook/chapter11.py
fncbook/chapter13.py
fncbook/tests/__init__.py
fncbook/tests/test_chapter1.py
fncbook/tests/test_chapter10.py
fncbook/tests/test_chapter11.py
fncbook/tests/test_chapter13.py
fncbook/tests/test_chapter2.py
fncbook/tests/test_chapter3.py
fncbook/tests/test_chapter4.py
fncbook/tests/test_chapter5.py
fncbook/tests/test_chapter6.py
fncbook/tests/test_chapter8.py
fncbook/tests/test_chapter9.py
fncbook-0.1.4.dist-info/licenses/LICENSE
fncbook-0.1.4.dist-info/METADATA
fncbook-0.1.4.dist-info/WHEEL
fncbook-0.1.4.dist-info/top_level.txt
fncbook-0.1.4.dist-info/RECORD
