Metadata-Version: 2.4
Name: fncbook
Version: 0.1.4
Summary: Codes for the book *Fundamentals of Numerical Computation*
Author-email: "Tobin A. Driscoll" <driscoll@udel.edu>
License: MIT License
Project-URL: Homepage, https://github.com/fncbook/fncbook.py
Project-URL: Issues, https://github.com/fncbook/fncbook.py/issues
Project-URL: Documentation, https://fncbook.github.io/fnc/
Keywords: numerical analysis,textbook,computational math,math,education
Classifier: Programming Language :: Python :: 3
Classifier: License :: OSI Approved :: MIT License
Classifier: Operating System :: OS Independent
Classifier: Intended Audience :: Education
Classifier: Topic :: Scientific/Engineering :: Mathematics
Requires-Python: >=3.8
License-File: LICENSE
Requires-Dist: numpy
Requires-Dist: scipy
Dynamic: license-file
